{
  "history" : "Yon-Gay is named after a famous general during the Ko-gore-yo Dynasty, Yon-Gay-So-Moon. The forty-nine movements refer to the last two figures of the year six-hundred-forty-nine A.D., the year he forced the Tang Dynasty to quit Korea after destroying nearly three-hundred-thousand of their troops at Ansee Sung.",
  "movements" :
  [
    {
      "description" : ""
    },
    {
      "description" : ""
    },
    {
      "description" : ""
    },
    {
      "description" : ""
    },
    {
      "description" : ""
    },
    {
      "description" : ""
    },
    {
      "description" : ""
    },
    {
      "description" : ""
    },
    {
      "description" : ""
    },
    {
      "description" : ""
    },
    {
      "description" : ""
    },
    {
      "description" : ""
    },
    {
      "description" : ""
    },
    {
      "description" : ""
    },
    {
      "description" : ""
    },
    {
      "description" : ""
    },
    {
      "description" : ""
    },
    {
      "description" : ""
    }
  ]
}
