{
  "history" : "Yon-Gae history",
  "movements" :
  [
    {
      "shortDescription" : "",
      "fullDescription" : ""
    },
    {
      "shortDescription" : "",
      "fullDescription" : ""
    },
    {
      "shortDescription" : "",
      "fullDescription" : ""
    },
    {
      "shortDescription" : "",
      "fullDescription" : ""
    },
    {
      "shortDescription" : "",
      "fullDescription" : ""
    },
    {
      "shortDescription" : "",
      "fullDescription" : ""
    },
    {
      "shortDescription" : "",
      "fullDescription" : ""
    },
    {
      "shortDescription" : "",
      "fullDescription" : ""
    },
    {
      "shortDescription" : "",
      "fullDescription" : ""
    },
    {
      "shortDescription" : "",
      "fullDescription" : ""
    },
    {
      "shortDescription" : "",
      "fullDescription" : ""
    },
    {
      "shortDescription" : "",
      "fullDescription" : ""
    },
    {
      "shortDescription" : "",
      "fullDescription" : ""
    },
    {
      "shortDescription" : "",
      "fullDescription" : ""
    },
    {
      "shortDescription" : "",
      "fullDescription" : ""
    },
    {
      "shortDescription" : "",
      "fullDescription" : ""
    },
    {
      "shortDescription" : "",
      "fullDescription" : ""
    },
    {
      "shortDescription" : "",
      "fullDescription" : ""
    }
  ]
}
